farbe.py
farbe-0.1.dist-info/METADATA
farbe-0.1.dist-info/RECORD
farbe-0.1.dist-info/WHEEL
farbe-0.1.dist-info/top_level.txt
