Metadata-Version: 2.1
Name: farbe
Version: 0.1
Summary: farbe lets you use colorized outputs in Python.
Home-page: https://github.com/morinokami/farbe
Author: Shinya Fujino
Author-email: shf0811@gmail.com
License: MIT
Platform: UNKNOWN
Classifier: Development Status :: 4 - Beta
Classifier: Environment :: Console
Classifier: License :: OSI Approved :: MIT License
Classifier: Operating System :: MacOS
Classifier: Operating System :: POSIX :: Linux
Classifier: Programming Language :: Python :: 3
